single_session/__init__.py
single_session/admin.py
single_session/apps.py
single_session/models.py
single_session/signals.py
single_session/tests.py
single_session/locale/nl/LC_MESSAGES/django.mo
single_session/locale/nl/LC_MESSAGES/django.po
single_session/migrations/0001_initial.py
single_session/migrations/__init__.py
django_single_session-0.2.0.dist-info/LICENSE
django_single_session-0.2.0.dist-info/METADATA
django_single_session-0.2.0.dist-info/WHEEL
django_single_session-0.2.0.dist-info/top_level.txt
django_single_session-0.2.0.dist-info/RECORD
